picage/__init__.py
picage/_version.py
picage/helpers.py
picage/model.py
picage/docs/__init__.py
picage-0.2.2.dist-info/AUTHORS.rst
picage-0.2.2.dist-info/LICENSE.txt
picage-0.2.2.dist-info/METADATA
picage-0.2.2.dist-info/WHEEL
picage-0.2.2.dist-info/top_level.txt
picage-0.2.2.dist-info/RECORD
